invert_pdf_colors/__init__.py
invert_pdf_colors/invert.py
invert_pdf_colors-0.3.dist-info/LICENSE
invert_pdf_colors-0.3.dist-info/METADATA
invert_pdf_colors-0.3.dist-info/WHEEL
invert_pdf_colors-0.3.dist-info/entry_points.txt
invert_pdf_colors-0.3.dist-info/top_level.txt
invert_pdf_colors-0.3.dist-info/RECORD
