Metadata-Version: 2.1
Name: invert_pdf_colors
Version: 0.3
Summary: A Python library to invert PDF text and background colors.
Author: Your Name
Author-email: your.email@example.com
License-File: LICENSE
Requires-Dist: PyMuPDF
